setup.py
python_rco.egg-info/PKG-INFO
python_rco.egg-info/SOURCES.txt
python_rco.egg-info/dependency_links.txt
python_rco.egg-info/requires.txt
python_rco.egg-info/top_level.txt
rco/__init__.py
rco/async.py
rco/base.py
rco/client.py
rco/compat.py
rco/errors.py
rco/interfaces.py
rco/naming.py
rco/plugins.py
rco/security.py
rco/stdlib.py
rco/tempdb.py
rco/tickets.py
rco/tools.py