Metadata-Version: 1.0
Name: python-rco
Version: 0.3.0
Summary: RC Online services library
Home-page: UNKNOWN
Author: Ruslan V. Uss
Author-email: unclerus@gmail.com
License: LGPLv3
Platform: UNKNOWN
